{
  "name": "data-toolbox",
  "title": "Data Toolbox for FoundryVTT",
  "description": "Tools for generating/manipulating data (compendiums). For example, it can be used for generating a compendium from a CSV file.",
  "version": "1.7.0",
  "author": "Sven Werlen",
  "scripts": ["data-toolbox.js", "scripts/d3/d3.min.js", "scripts/d3-fetch/d3-fetch.min.js", "scripts/letscontribute.js", "scripts/jdd/jdd.js"],
  "styles": ["data-toolbox.css"],
  "languages": [
    {
      "lang": "en",
      "name": "English",
      "path": "lang/en.json"
    },
    {
      "lang": "fr",
      "name": "French",
      "path": "lang/fr.json"
    }
  ],
  "packs": [
    {
      "name": "data-macros",
      "label": "Data Macros",
      "path": "./packs/data-macros.db",
      "entity": "Macro"
    }
  ],
  "url": "https://github.com/SvenWerlen/fvtt-data-toolbox",
  "download": "https://github.com/SvenWerlen/fvtt-data-toolbox/archive/v-1.7.0.zip",
  "manifest": "https://raw.githubusercontent.com/SvenWerlen/fvtt-data-toolbox/master/module.json",
  "minimumCoreVersion": "0.6.0",
  "compatibleCoreVersion": "1.0.0"
}
